README.md
setup.py
example_publish_pypi_qytest/__init__.py
example_publish_pypi_qytest/custom_sklearn.py
example_publish_pypi_qytest.egg-info/PKG-INFO
example_publish_pypi_qytest.egg-info/SOURCES.txt
example_publish_pypi_qytest.egg-info/dependency_links.txt
example_publish_pypi_qytest.egg-info/requires.txt
example_publish_pypi_qytest.egg-info/top_level.txt