Metadata-Version: 2.1
Name: example-publish-pypi-qytest
Version: 0.0.4
Summary: example of publishing pypi package
Home-page: UNKNOWN
Author: Qiuyu Lian
Author-email: qiuyu.lian@sjtu.edu.cn
License: MIT
Platform: UNKNOWN
